pyqtspinner/__init__.py
pyqtspinner/configurator.py
pyqtspinner/spinner.py
pyqtspinner-1.0.2.dist-info/entry_points.txt
pyqtspinner-1.0.2.dist-info/LICENSE.md
pyqtspinner-1.0.2.dist-info/WHEEL
pyqtspinner-1.0.2.dist-info/METADATA
pyqtspinner-1.0.2.dist-info/RECORD
