Metadata-Version: 2.1
Name: pyqtspinner
Version: 1.0.2
Summary: Waiting spinner for PyQt5
Home-page: https://github.com/fbjorn/QtWaitingSpinner
License: MIT
Author: Denis
Author-email: fbjorn@users.noreply.github.com
Requires-Python: >=3.7
Classifier: Environment :: X11 Applications
Classifier: Environment :: X11 Applications :: Qt
Classifier: Intended Audience :: Developers
Classifier: Intended Audience :: Information Technology
Classifier: License :: OSI Approved :: MIT License
Classifier: Operating System :: OS Independent
Classifier: Programming Language :: Python
Classifier: Programming Language :: Python :: 3
Classifier: Programming Language :: Python :: 3 :: Only
Classifier: Programming Language :: Python :: 3.10
Classifier: Programming Language :: Python :: 3.7
Classifier: Programming Language :: Python :: 3.8
Classifier: Programming Language :: Python :: 3.9
Classifier: Topic :: Software Development
Classifier: Topic :: Software Development :: Libraries
Classifier: Topic :: Software Development :: Libraries :: Python Modules
Requires-Dist: PyQt5 (>5.8)
Project-URL: Repository, https://github.com/fbjorn/QtWaitingSpinner
